odoo8_addon_product_variant_csv_import-8.0.1.0.0.99.dev16-py2.7-nspkg.pth
odoo8_addon_product_variant_csv_import-8.0.1.0.0.99.dev16.dist-info/DESCRIPTION.rst
odoo8_addon_product_variant_csv_import-8.0.1.0.0.99.dev16.dist-info/METADATA
odoo8_addon_product_variant_csv_import-8.0.1.0.0.99.dev16.dist-info/RECORD
odoo8_addon_product_variant_csv_import-8.0.1.0.0.99.dev16.dist-info/WHEEL
odoo8_addon_product_variant_csv_import-8.0.1.0.0.99.dev16.dist-info/metadata.json
odoo8_addon_product_variant_csv_import-8.0.1.0.0.99.dev16.dist-info/namespace_packages.txt
odoo8_addon_product_variant_csv_import-8.0.1.0.0.99.dev16.dist-info/top_level.txt
odoo_addons/product_variant_csv_import/README.rst
odoo_addons/product_variant_csv_import/__init__.py
odoo_addons/product_variant_csv_import/__openerp__.py
odoo_addons/product_variant_csv_import/product.py
odoo_addons/product_variant_csv_import/product_view.xml
odoo_addons/product_variant_csv_import/i18n/ca.po
odoo_addons/product_variant_csv_import/i18n/de.po
odoo_addons/product_variant_csv_import/i18n/el_GR.po
odoo_addons/product_variant_csv_import/i18n/es.po
odoo_addons/product_variant_csv_import/i18n/es_ES.po
odoo_addons/product_variant_csv_import/i18n/eu.po
odoo_addons/product_variant_csv_import/i18n/fi.po
odoo_addons/product_variant_csv_import/i18n/fr.po
odoo_addons/product_variant_csv_import/i18n/fr_CH.po
odoo_addons/product_variant_csv_import/i18n/fr_FR.po
odoo_addons/product_variant_csv_import/i18n/gl.po
odoo_addons/product_variant_csv_import/i18n/hr.po
odoo_addons/product_variant_csv_import/i18n/hr_HR.po
odoo_addons/product_variant_csv_import/i18n/it.po
odoo_addons/product_variant_csv_import/i18n/nl.po
odoo_addons/product_variant_csv_import/i18n/nl_NL.po
odoo_addons/product_variant_csv_import/i18n/product_variant_csv_import.pot
odoo_addons/product_variant_csv_import/i18n/pt.po
odoo_addons/product_variant_csv_import/i18n/pt_BR.po
odoo_addons/product_variant_csv_import/i18n/ro.po
odoo_addons/product_variant_csv_import/i18n/ru.po
odoo_addons/product_variant_csv_import/i18n/sk.po
odoo_addons/product_variant_csv_import/i18n/sl.po
odoo_addons/product_variant_csv_import/i18n/tr.po
odoo_addons/product_variant_csv_import/i18n/tr_TR.po
odoo_addons/product_variant_csv_import/i18n/vi_VN.po
odoo_addons/product_variant_csv_import/i18n/zh_CN.po
odoo_addons/product_variant_csv_import/sample_csv/product.attribute.csv
odoo_addons/product_variant_csv_import/sample_csv/product.attribute.value.csv
odoo_addons/product_variant_csv_import/sample_csv/product.template.csv
